{
  "icon": "/icons/icon.PNG",
  "title": "BUCTBASE",
  "maxItems": 150,
  "googleFont": "Rubik",
  "googleFontWeights": [
    "400",
    "600"
  ],
  "footer": "Powered by <a class=\"hover:underline\" href=\"https://github.com/spencerwooo/onedrive-vercel-index\" target=\"_blank\" rel=\"noopener noreferrer\">onedrive-vercel-index</a>. Made with ❤ by ZAC & Oliver.",
  "protectedRoutes": [
    "/内部资料"
  ],
  "contact": {
    "email": "mailto:zhadui@buctbase.com",
    "github": "https://github.com/buctbase/buctbase",
    "qq": "https://qm.qq.com/cgi-bin/qm/qr?k=FdhVoyE5kG44805-6slZwoM3pw9kmFl6&jump_from=webapi"
  }
}
